byted_overpass_iescontent_aigc_review_process/__init__.py
byted_overpass_iescontent_aigc_review_process-0.0.1.dist-info/METADATA
byted_overpass_iescontent_aigc_review_process-0.0.1.dist-info/WHEEL
byted_overpass_iescontent_aigc_review_process-0.0.1.dist-info/top_level.txt
byted_overpass_iescontent_aigc_review_process-0.0.1.dist-info/RECORD
